odoo9_addon_hr_expense_analytic_distribution-9.0.1.0.0-py2.7-nspkg.pth
odoo9_addon_hr_expense_analytic_distribution-9.0.1.0.0.dist-info/DESCRIPTION.rst
odoo9_addon_hr_expense_analytic_distribution-9.0.1.0.0.dist-info/METADATA
odoo9_addon_hr_expense_analytic_distribution-9.0.1.0.0.dist-info/RECORD
odoo9_addon_hr_expense_analytic_distribution-9.0.1.0.0.dist-info/WHEEL
odoo9_addon_hr_expense_analytic_distribution-9.0.1.0.0.dist-info/metadata.json
odoo9_addon_hr_expense_analytic_distribution-9.0.1.0.0.dist-info/namespace_packages.txt
odoo9_addon_hr_expense_analytic_distribution-9.0.1.0.0.dist-info/top_level.txt
odoo_addons/hr_expense_analytic_distribution/README.rst
odoo_addons/hr_expense_analytic_distribution/__init__.py
odoo_addons/hr_expense_analytic_distribution/__openerp__.py
odoo_addons/hr_expense_analytic_distribution/i18n/de.po
odoo_addons/hr_expense_analytic_distribution/i18n/es.po
odoo_addons/hr_expense_analytic_distribution/i18n/fi.po
odoo_addons/hr_expense_analytic_distribution/i18n/fr.po
odoo_addons/hr_expense_analytic_distribution/i18n/hr_expense_analytic_plans.pot
odoo_addons/hr_expense_analytic_distribution/i18n/nl.po
odoo_addons/hr_expense_analytic_distribution/i18n/pt_BR.po
odoo_addons/hr_expense_analytic_distribution/i18n/sl.po
odoo_addons/hr_expense_analytic_distribution/models/__init__.py
odoo_addons/hr_expense_analytic_distribution/models/hr_expense.py
odoo_addons/hr_expense_analytic_distribution/static/description/icon.png
odoo_addons/hr_expense_analytic_distribution/tests/__init__.py
odoo_addons/hr_expense_analytic_distribution/tests/test_hr_expense_analytic_distribution.py
odoo_addons/hr_expense_analytic_distribution/views/hr_expense.xml
